[{"type":"Coastal Sea","roll":0,"location":"Tile","combat_width":30},{"type":"Crossing river","location":"Border","roll":-1,"combat_width":0},{"type":"Crossing strait","location":"Border","roll":-2,"combat_width":0},{"type":"Desert","roll":0,"location":"Tile","combat_width":28},{"type":"Duel","location":"Tile","roll":0,"combat_width":1},{"type":"Farmland","roll":0,"location":"Tile","combat_width":30},{"type":"Forest","roll":-1,"location":"Tile","combat_width":20},{"type":"Hills","roll":-1,"location":"Tile","combat_width":20},{"type":"Impassable","roll":0,"location":"Tile","combat_width":10},{"type":"Jungle","roll":0,"location":"Tile","combat_width":18},{"type":"Marsh","roll":-1,"location":"Tile","combat_width":18},{"type":"Mountains","roll":-2,"location":"Tile","combat_width":16},{"type":"None","location":"Border","roll":0,"combat_width":0},{"type":"Open Sea","roll":0,"location":"Tile","combat_width":50},{"type":"Plains","roll":0,"location":"Tile","combat_width":40},{"type":"River","roll":-1,"location":"Tile","combat_width":10}]